decotools/__init__.py
decotools/_version.py
decotools/tests/__init__.py
decotools/tests/conftest.py
decotools/tests/test_examples.py
decotools/tests/test_helloworld.py
decotools/tests/test_wraps.py
decotools-0.0.1.dist-info/AUTHORS.rst
decotools-0.0.1.dist-info/LICENSE
decotools-0.0.1.dist-info/METADATA
decotools-0.0.1.dist-info/WHEEL
decotools-0.0.1.dist-info/entry_points.txt
decotools-0.0.1.dist-info/top_level.txt
decotools-0.0.1.dist-info/RECORD
