Metadata-Version: 2.1
Name: decotools
Version: 0.0.1
Summary: This is a decorator toolbox.
Home-page: https://github.com/ke-zhang-rd/decotools
Author: Ke Zhang
Author-email: kezhang0729@gmail.com
License: BSD (3-clause)
Platform: UNKNOWN
Classifier: Development Status :: 2 - Pre-Alpha
Classifier: Natural Language :: English
Classifier: Programming Language :: Python :: 3
Requires-Python: >=3.8
